{"mc":{
	"0":{
		"frameRate":12,
		"labels":[
			{"name":"0","frame":1,"end":15}
			
			],
		"events":[
			
			],
		"frames":[
			
			{
			"res":"wait_61",
			"x":-249,
			"y":9
			},
			{
			"res":"wait_62",
			"x":-257,
			"y":9
			},
			{
			"res":"wait_63",
			"x":-261,
			"y":9
			},
			{
			"res":"wait_64",
			"x":-262,
			"y":9
			},
			{
			"res":"wait_65",
			"x":-257,
			"y":9
			},
			{
			"res":"wait_66",
			"x":-251,
			"y":9
			},
			{
			"res":"wait_67",
			"x":-243,
			"y":9
			},
			{
			"res":"wait_68",
			"x":-237,
			"y":9
			},
			{
			"res":"wait_69",
			"x":-233,
			"y":8
			},
			{
			"res":"wait_70",
			"x":-229,
			"y":5
			},
			{
			"res":"wait_71",
			"x":-228,
			"y":2
			},
			{
			"res":"wait_72",
			"x":-229,
			"y":-1
			},
			{
			"res":"wait_73",
			"x":-225,
			"y":-4
			},
			{
			"res":"wait_74",
			"x":-227,
			"y":-6
			},
			{
			"res":"wait_75",
			"x":-231,
			"y":-8
			}
			]
}},
	"res":{
		"wait_71":{"x":541,"y":355,"w":531,"h":349},
		"wait_69":{"x":1078,"y":1368,"w":529,"h":343},
		"wait_72":{"x":0,"y":716,"w":534,"h":352},
		"wait_70":{"x":549,"y":1058,"w":529,"h":346},
		"wait_75":{"x":0,"y":0,"w":541,"h":359},
		"wait_65":{"x":1073,"y":342,"w":544,"h":342},
		"wait_73":{"x":541,"y":0,"w":532,"h":355},
		"wait_68":{"x":545,"y":1410,"w":530,"h":342},
		"wait_61":{"x":534,"y":716,"w":538,"h":342},
		"wait_62":{"x":0,"y":1410,"w":545,"h":342},
		"wait_64":{"x":1073,"y":0,"w":550,"h":342},
		"wait_66":{"x":1072,"y":684,"w":538,"h":342},
		"wait_63":{"x":0,"y":1068,"w":549,"h":342},
		"wait_74":{"x":0,"y":359,"w":536,"h":357},
		"wait_67":{"x":1078,"y":1026,"w":533,"h":342}
	}}