{"mc":{
	"0":{
		"frameRate":12,
		"labels":[
			{"name":"0","frame":1,"end":15}
			
			],
		"events":[
			
			],
		"frames":[
			
			{
			"res":"wait_181",
			"x":-231,
			"y":-19
			},
			{
			"res":"wait_182",
			"x":-230,
			"y":-19
			},
			{
			"res":"wait_183",
			"x":-230,
			"y":-20
			},
			{
			"res":"wait_184",
			"x":-230,
			"y":-21
			},
			{
			"res":"wait_185",
			"x":-234,
			"y":-23
			},
			{
			"res":"wait_186",
			"x":-242,
			"y":-22
			},
			{
			"res":"wait_187",
			"x":-254,
			"y":-20
			},
			{
			"res":"wait_188",
			"x":-265,
			"y":-19
			},
			{
			"res":"wait_189",
			"x":-274,
			"y":-16
			},
			{
			"res":"wait_190",
			"x":-282,
			"y":-13
			},
			{
			"res":"wait_191",
			"x":-281,
			"y":-11
			},
			{
			"res":"wait_192",
			"x":-270,
			"y":-10
			},
			{
			"res":"wait_193",
			"x":-257,
			"y":-9
			},
			{
			"res":"wait_194",
			"x":-249,
			"y":-8
			},
			{
			"res":"wait_195",
			"x":-239,
			"y":-7
			}
			]
}},
	"res":{
		"wait_193":{"x":1110,"y":1099,"w":551,"h":358},
		"wait_184":{"x":573,"y":718,"w":545,"h":371},
		"wait_187":{"x":0,"y":731,"w":566,"h":368},
		"wait_182":{"x":1162,"y":359,"w":543,"h":370},
		"wait_186":{"x":0,"y":1099,"w":556,"h":371},
		"wait_194":{"x":1110,"y":1457,"w":543,"h":358},
		"wait_190":{"x":579,"y":0,"w":583,"h":360},
		"wait_188":{"x":0,"y":364,"w":573,"h":367},
		"wait_181":{"x":1118,"y":729,"w":543,"h":370},
		"wait_189":{"x":0,"y":0,"w":579,"h":364},
		"wait_192":{"x":579,"y":360,"w":565,"h":358},
		"wait_195":{"x":556,"y":1460,"w":534,"h":357},
		"wait_185":{"x":0,"y":1470,"w":549,"h":373},
		"wait_183":{"x":566,"y":1089,"w":544,"h":371},
		"wait_191":{"x":1162,"y":0,"w":578,"h":359}
	}}